sysgit/__init__.py
sysgit/__meta__.py
sysgit/test.py
sysgit-0.1.0.dist-info/METADATA
sysgit-0.1.0.dist-info/WHEEL
sysgit-0.1.0.dist-info/top_level.txt
sysgit-0.1.0.dist-info/RECORD
