Metadata-Version: 2.2
Name: sysgit
Version: 0.1.0
Summary: When the internal logic for this package is implemented, more detail will be added.
Requires-Python: <=3.13,>=3.10
